{
  "action": "action.php",
  "attributes": "class=\"this\" id=\"that\"",
  "name": "myForm",
  "items": [
    {
      "element": "input",
      "event": {
        "handler": "click",
        "function": "console.log('hello')"
      },
      "type": "text",
      "name": "aName",
      "placeholder": "aPlaceholder",
      "value": "aValue",
      "label": "this is a label"
    },
    {
      "element": "input",
      "type": "text",
      "name": "anotherName",
      "placeholder": "aPlaceholder",
      "value": "aValue"
    },
    {
      "element": "textarea",
      "name": "aTextArea",
      "width": "20",
      "height": "5",
      "value": "aValue",
      "label": "this is a label"
    },
    {
      "element": "input",
      "type": "checkbox",
      "name": "aCheckbox",
      "value": "aValue",
      "label": "check this",
      "checked": "true"
    },
    {
      "element": "select",
      "name": "thisName",
      "options": [
        {
          "name": "hi",
          "value": "hello"
        },
        {
          "name": "bye",
          "value": "goodbye"
        }
      ]
    }
  ]
}